{
  "profile_id": 3635145,
  "alias": "Prinz Kay1",
  "rating": 1038,
  "wins": 29,
  "losses": 26,
  "gamesCount": 55,
  "winRate": 53,
  "lastPlayedAt": 1783636271,
  "country": "de",
  "merged_ids": [],
  "ratingHistory": [
    1000,
    1057,
    1011,
    972,
    931,
    981,
    1027,
    987,
    1029,
    1064,
    1094,
    1059,
    1088,
    1058,
    1035,
    1061,
    1039,
    1059,
    1081,
    1098,
    1080,
    1094,
    1108,
    1121,
    1135,
    1115,
    1126,
    1106,
    1088,
    1068,
    1049,
    1032,
    1018,
    1035,
    1052,
    1071,
    1088,
    1102,
    1084,
    1098,
    1107,
    1089,
    1073,
    1056,
    1071,
    1055,
    1069,
    1084,
    1100,
    1113,
    1096,
    1077,
    1059,
    1071,
    1056,
    1038
  ],
  "recentMatches": [
    {
      "matchId": 467146980,
      "description": "10x3x Bamboo Nothing",
      "mapname": "Bamboo Nothing_Paren_V4",
      "timestamp": 1775077320,
      "outcome": "win",
      "preRating": 1071,
      "postRating": 1088,
      "eloChange": 17,
      "civ": "Unknown",
      "teamAvgElo": 1056,
      "opponentAvgElo": 1088,
      "teammates": [
        "MrSniffers",
        "Gab Freecs",
        "CrazyKaelby"
      ],
      "opponents": [
        "東亞窪地",
        "QTJ钱塘江客",
        "Carmillum",
        "matt"
      ]
    },
    {
      "matchId": 467235531,
      "description": "10x 3x bamboo",
      "mapname": "Bamboo Nothing_Paren_V4",
      "timestamp": 1775105220,
      "outcome": "win",
      "preRating": 1088,
      "postRating": 1102,
      "eloChange": 14,
      "civ": "Unknown",
      "teamAvgElo": 1009,
      "opponentAvgElo": 1045,
      "teammates": [
        "Rita De Valencia",
        "Dutchigander",
        "Lykerya"
      ],
      "opponents": [
        "Chuckyllo4417",
        "RedBullWOLOLO26",
        "[B] Cannino",
        "Axobada"
      ]
    },
    {
      "matchId": 467334482,
      "description": "Bamboo 10x 3x 4v4",
      "mapname": "Bamboo Nothing - Scorpyon De",
      "timestamp": 1775151660,
      "outcome": "loss",
      "preRating": 1102,
      "postRating": 1084,
      "eloChange": -18,
      "civ": "Unknown",
      "teamAvgElo": 1093,
      "opponentAvgElo": 1050,
      "teammates": [
        "Mehandor",
        "QTJ钱塘江客",
        "konishika"
      ],
      "opponents": [
        "alexw",
        "kaka52pk",
        "Boocer",
        "Mad08jojo"
      ]
    },
    {
      "matchId": 467457656,
      "description": "BAMBOO 10x - 3x  **NO BEGINNER",
      "mapname": "Bamboo Nothing - Scorpyon De",
      "timestamp": 1775191140,
      "outcome": "win",
      "preRating": 1084,
      "postRating": 1098,
      "eloChange": 14,
      "civ": "Unknown",
      "teamAvgElo": 1056,
      "opponentAvgElo": 1040,
      "teammates": [
        "zDeathManz",
        "dRea",
        "Feid"
      ],
      "opponents": [
        "BeatsNArt",
        "GrandUni",
        "weakest man in bayader",
        "[B] Cannino"
      ]
    },
    {
      "matchId": 467586627,
      "description": "10x 3x bamboo",
      "mapname": "my map",
      "timestamp": 1775217197,
      "outcome": "win",
      "preRating": 1098,
      "postRating": 1107,
      "eloChange": 9,
      "civ": "Koreans",
      "teamAvgElo": 1042,
      "opponentAvgElo": 939,
      "teammates": [
        "_S_",
        "Mad08jojo",
        "crowmoly"
      ],
      "opponents": [
        "Lykerya",
        "VeasnaTDM",
        "kc",
        "shadghost"
      ]
    },
    {
      "matchId": 467610744,
      "description": "10x 3x bamboo random civ - frank sucks",
      "mapname": "Bamboo Nothing_Paren_V4",
      "timestamp": 1775250240,
      "outcome": "loss",
      "preRating": 1107,
      "postRating": 1089,
      "eloChange": -18,
      "civ": "Unknown",
      "teamAvgElo": 1068,
      "opponentAvgElo": 1058,
      "teammates": [
        "mamudogurbanniyedoğdun",
        "LonelyKnight",
        "okfkg173"
      ],
      "opponents": [
        "bijiyumo",
        "kaka52pk",
        "Max",
        "tonkatumura"
      ]
    },
    {
      "matchId": 467896947,
      "description": "10x3x Bamboo Nothing",
      "mapname": "Bamboo Nothing_Paren_V4",
      "timestamp": 1775338680,
      "outcome": "loss",
      "preRating": 1089,
      "postRating": 1073,
      "eloChange": -16,
      "civ": "Unknown",
      "teamAvgElo": 1067,
      "opponentAvgElo": 1093,
      "teammates": [
        "UbaneMess",
        "tonkatumura",
        "取款机ATM"
      ],
      "opponents": [
        "東亞窪地",
        "Lumedge",
        "kekekeya",
        "ISwaZz"
      ]
    },
    {
      "matchId": 468167562,
      "description": "10x3x Bamboo Nothing",
      "mapname": "Bamboo Nothing_Paren_V4",
      "timestamp": 1775426040,
      "outcome": "loss",
      "preRating": 1073,
      "postRating": 1056,
      "eloChange": -17,
      "civ": "Unknown",
      "teamAvgElo": 1016,
      "opponentAvgElo": 1045,
      "teammates": [
        "crowmoly",
        "fxsound",
        "Rosey Toes"
      ],
      "opponents": [
        "東亞窪地",
        "Miwa",
        "Frederick",
        "Sam"
      ]
    },
    {
      "matchId": 468737271,
      "description": "frank sucks - 10x 3x bamboo random civ",
      "mapname": "Bamboo Nothing_Paren_V4",
      "timestamp": 1775623920,
      "outcome": "win",
      "preRating": 1056,
      "postRating": 1071,
      "eloChange": 15,
      "civ": "Unknown",
      "teamAvgElo": 1046,
      "opponentAvgElo": 1041,
      "teammates": [
        "Wraith",
        "Apocalypto",
        "Sensei"
      ],
      "opponents": [
        "bijiyumo",
        "LUIS123456E",
        "OhSheeep",
        "ElCapi7766"
      ]
    },
    {
      "matchId": 468843258,
      "description": "bamboo nothing 10x 3x",
      "mapname": "Bamboo Nothing V1 [Scorpyon]",
      "timestamp": 1775673780,
      "outcome": "loss",
      "preRating": 1071,
      "postRating": 1055,
      "eloChange": -16,
      "civ": "Unknown",
      "teamAvgElo": 1058,
      "opponentAvgElo": 1065,
      "teammates": [
        "Lumedge",
        "Hyge",
        "The Chill Architect"
      ],
      "opponents": [
        "AceTrooper",
        "beat",
        "McKrakfejs",
        "i kun 2.5"
      ]
    },
    {
      "matchId": 470244406,
      "description": "10x bamboo nothing",
      "mapname": "Bamboo Nothing - Scorpyon De",
      "timestamp": 1776140340,
      "outcome": "win",
      "preRating": 1055,
      "postRating": 1069,
      "eloChange": 14,
      "civ": "Unknown",
      "teamAvgElo": 1028,
      "opponentAvgElo": 1012,
      "teammates": [
        "ThrillerKillah17",
        "TR.elephantman",
        "El Barto"
      ],
      "opponents": [
        "idefixyeee",
        "Keishi",
        "Bene",
        "Goodsoup"
      ]
    },
    {
      "matchId": 477227456,
      "description": "BAMBOO NOTHING 10x civ 3x tech",
      "mapname": "Bamboo Nothing - Scorpyon De",
      "timestamp": 1778602800,
      "outcome": "win",
      "preRating": 1069,
      "postRating": 1084,
      "eloChange": 15,
      "civ": "Unknown",
      "teamAvgElo": 1019,
      "opponentAvgElo": 1055,
      "teammates": [
        "mrkus.shlz",
        "Soviet Union",
        "Arktik"
      ],
      "opponents": [
        "476055690",
        "samseryd",
        "Zak",
        "DrKahazad"
      ]
    },
    {
      "matchId": 484754987,
      "description": "BAMBOO 10x3xtech",
      "mapname": "Bamboo Nothing - Scorpyon De",
      "timestamp": 1781282460,
      "outcome": "win",
      "preRating": 1084,
      "postRating": 1100,
      "eloChange": 16,
      "civ": "Jurchens",
      "teamAvgElo": 1075,
      "opponentAvgElo": 1095,
      "teammates": [
        "iamatthe.hell",
        "Captain Stripes",
        "鱼浆"
      ],
      "opponents": [
        "EzraSkywalker96",
        "nooblet3300",
        "bijiyumo",
        "OldManofStorr"
      ]
    },
    {
      "matchId": 484851491,
      "description": "BAMBOO 10x3xtech",
      "mapname": "Bamboo Nothing - Scorpyon De",
      "timestamp": 1781313240,
      "outcome": "win",
      "preRating": 1100,
      "postRating": 1113,
      "eloChange": 13,
      "civ": "Slavs",
      "teamAvgElo": 1029,
      "opponentAvgElo": 1033,
      "teammates": [
        "iamatthe.hell",
        "Russie",
        "RawChicken"
      ],
      "opponents": [
        "NothingAtAll11",
        "Lumedge",
        "Pope Leo I.",
        "KK"
      ]
    },
    {
      "matchId": 489980490,
      "description": "4vs4 10x 3x shared civ bonus, random civ",
      "mapname": "Bamboo Nothing_Paren_V4",
      "timestamp": 1783186140,
      "outcome": "loss",
      "preRating": 1113,
      "postRating": 1096,
      "eloChange": -17,
      "civ": "Celts",
      "teamAvgElo": 1068,
      "opponentAvgElo": 1098,
      "teammates": [
        "fxsound",
        "Monk",
        "mothysime11"
      ],
      "opponents": [
        "pandalam",
        "yimacs_yoyoyo",
        "kaka52pk",
        "Terry"
      ]
    },
    {
      "matchId": 490280859,
      "description": "Bamboo nothing 10X3X",
      "mapname": "my map",
      "timestamp": 1783262969,
      "outcome": "loss",
      "preRating": 1096,
      "postRating": 1077,
      "eloChange": -19,
      "civ": "Unknown",
      "teamAvgElo": 1033,
      "opponentAvgElo": 1020,
      "teammates": [
        "yxsko93",
        "Charu",
        "master"
      ],
      "opponents": [
        "Mandriao",
        "tonkatumura",
        "Zak",
        "Nigerian Farmer"
      ]
    },
    {
      "matchId": 490502443,
      "description": "Bamboo nothing 10X3X",
      "mapname": "my map",
      "timestamp": 1783349891,
      "outcome": "loss",
      "preRating": 1077,
      "postRating": 1059,
      "eloChange": -18,
      "civ": "Magyars",
      "teamAvgElo": 1057,
      "opponentAvgElo": 1040,
      "teammates": [
        "Mehandor",
        "ElmoWithoutL",
        "LonelyKnight"
      ],
      "opponents": [
        "yxsko93",
        "Filtz",
        "Bao Oninon",
        "Boocer"
      ]
    },
    {
      "matchId": 490779007,
      "description": "10x 3x bamboo",
      "mapname": "my map",
      "timestamp": 1783459090,
      "outcome": "win",
      "preRating": 1059,
      "postRating": 1071,
      "eloChange": 12,
      "civ": "Aztecs",
      "teamAvgElo": 1061,
      "opponentAvgElo": 970,
      "teammates": [
        "Lykerya",
        "Parenquima",
        "Abelardo4tojr"
      ],
      "opponents": [
        "og1kanooby",
        "ChiH",
        "Sleeper14",
        "Ruuder"
      ]
    },
    {
      "matchId": 491181660,
      "description": "10x 3x Bamboo - 10xshared.com",
      "mapname": "my map",
      "timestamp": 1783635384,
      "outcome": "loss",
      "preRating": 1071,
      "postRating": 1056,
      "eloChange": -15,
      "civ": "Gurjaras",
      "teamAvgElo": 990,
      "opponentAvgElo": 1089,
      "teammates": [
        "Parts",
        "Das_Constel",
        "Ellie91"
      ],
      "opponents": [
        "LonelyKnight",
        "TheRiceMan",
        "Apocalypto",
        "RA"
      ]
    },
    {
      "matchId": 491184751,
      "description": "10x 3x Bamboo - 10xshared.com",
      "mapname": "my map",
      "timestamp": 1783636271,
      "outcome": "loss",
      "preRating": 1056,
      "postRating": 1038,
      "eloChange": -18,
      "civ": "Koreans",
      "teamAvgElo": 999,
      "opponentAvgElo": 1019,
      "teammates": [
        "LonelyKnight",
        "Das_Constel",
        "Zak"
      ],
      "opponents": [
        "Parts",
        "Ellie91",
        "RA",
        "Apocalypto"
      ]
    }
  ]
}