{
  "profile_id": 3088660,
  "alias": "468673564",
  "rating": 903,
  "wins": 46,
  "losses": 76,
  "gamesCount": 122,
  "winRate": 38,
  "lastPlayedAt": 1784276825,
  "country": "au",
  "merged_ids": [],
  "ratingHistory": [
    1000,
    953,
    916,
    934,
    906,
    964,
    1011,
    1023,
    1057,
    1093,
    1115,
    1055,
    1075,
    1094,
    1066,
    1063,
    1046,
    1027,
    1043,
    1060,
    1090,
    1071,
    1084,
    1067,
    1061,
    1075,
    1089,
    1071,
    1067,
    1080,
    1061,
    1044,
    1013,
    998,
    985,
    969,
    956,
    996,
    980,
    997,
    981,
    981,
    965,
    985,
    972,
    948,
    938,
    924,
    946,
    953,
    940,
    960,
    946,
    933,
    939,
    953,
    941,
    928,
    906,
    929,
    917,
    904,
    885,
    907,
    899,
    922,
    913,
    923,
    910,
    898,
    886,
    931,
    952,
    942,
    961,
    938,
    928,
    915,
    903,
    913,
    903,
    891,
    914,
    901,
    881,
    872,
    862,
    883,
    862,
    856,
    880,
    904,
    886,
    909,
    931,
    921,
    902,
    893,
    914,
    903
  ],
  "recentMatches": [
    {
      "matchId": 482987126,
      "description": "Bamboo nothing 10X3X",
      "mapname": "Bamboo Nothing - Scorpyon De",
      "timestamp": 1780676820,
      "outcome": "loss",
      "preRating": 901,
      "postRating": 891,
      "eloChange": -10,
      "civ": "Teutons",
      "teamAvgElo": 984,
      "opponentAvgElo": 1031,
      "teammates": [
        "yxsko93",
        "Captain Stripes",
        "RawChicken"
      ],
      "opponents": [
        "DreamLegion",
        "fRy0ne",
        "UbaneMess",
        "lazykaiser94"
      ]
    },
    {
      "matchId": 482989358,
      "description": "bamboo nothing 10x",
      "mapname": "Bamboo Nothing V3 (Bali)",
      "timestamp": 1780678140,
      "outcome": "loss",
      "preRating": 891,
      "postRating": 881,
      "eloChange": -10,
      "civ": "Bulgarians",
      "teamAvgElo": 1027,
      "opponentAvgElo": 1022,
      "teammates": [
        "yxsko93",
        "nooblet3300",
        "[S33]ff"
      ],
      "opponents": [
        "[B] Zennith",
        "Fathrilocram",
        "fRy0ne",
        "DreamLegion"
      ]
    },
    {
      "matchId": 482992270,
      "description": "bamboo nothing 10x",
      "mapname": "Bamboo Nothing V3 (Bali)",
      "timestamp": 1780679700,
      "outcome": "loss",
      "preRating": 881,
      "postRating": 872,
      "eloChange": -9,
      "civ": "Berbers",
      "teamAvgElo": 961,
      "opponentAvgElo": 1034,
      "teammates": [
        "DreamLegion",
        "SickFishh",
        "BaldAfro"
      ],
      "opponents": [
        "[B] Zennith",
        "[S33]ff",
        "afranciscosa",
        "babeleo"
      ]
    },
    {
      "matchId": 483243328,
      "description": "bamboo nothing 10x",
      "mapname": "my map",
      "timestamp": 1780734053,
      "outcome": "loss",
      "preRating": 872,
      "postRating": 862,
      "eloChange": -10,
      "civ": "Tatars",
      "teamAvgElo": 994,
      "opponentAvgElo": 1018,
      "teammates": [
        "-[RDU]- Gorda America Forever",
        "丫丫真好看",
        "axiuluo"
      ],
      "opponents": [
        "[B] Zennith",
        "Eddie",
        "Marvel_123",
        "Yos'a"
      ]
    },
    {
      "matchId": 483208397,
      "description": "10x Shared 3xTech Bamboo Nothing",
      "mapname": "Bamboo Nothing_Paren_V4",
      "timestamp": 1780745040,
      "outcome": "win",
      "preRating": 862,
      "postRating": 883,
      "eloChange": 21,
      "civ": "Slavs",
      "teamAvgElo": 1024,
      "opponentAvgElo": 975,
      "teammates": [
        "{R} Parry",
        "-[RDU]- Gorda America Forever",
        "自闭男孩"
      ],
      "opponents": [
        "Ode To  A Pineapple",
        "Llucky Llama",
        "Master.Ji.ro.714",
        "DGHIR | NICOGP11"
      ]
    },
    {
      "matchId": 483471810,
      "description": "10x 3x shared tech Bamboo Nothing Random Civ",
      "mapname": "my map",
      "timestamp": 1780798624,
      "outcome": "loss",
      "preRating": 883,
      "postRating": 872,
      "eloChange": -11,
      "civ": "Malians",
      "teamAvgElo": 1020,
      "opponentAvgElo": 1006,
      "teammates": [
        "Wololoo",
        "Parts",
        "Bridge"
      ],
      "opponents": [
        "NoAgendaPODCAST",
        "476055690",
        "Nimu.-",
        "bpafree"
      ]
    },
    {
      "matchId": 483796197,
      "description": "bamboo nothing  10x",
      "mapname": "Bamboo Nothing V3 (Bali)",
      "timestamp": 1780919100,
      "outcome": "loss",
      "preRating": 872,
      "postRating": 862,
      "eloChange": -10,
      "civ": "Poles",
      "teamAvgElo": 1001,
      "opponentAvgElo": 1014,
      "teammates": [
        "edalmavuz",
        "Lady Uterus",
        "FrostByte"
      ],
      "opponents": [
        "[B] Zennith",
        "mack",
        "hoderebus",
        "Chuckyllo4417"
      ]
    },
    {
      "matchId": 483809026,
      "description": "10x Shared 3xTech Bamboo Nothing",
      "mapname": "Bamboo Nothing_Paren_V4",
      "timestamp": 1780925940,
      "outcome": "loss",
      "preRating": 862,
      "postRating": 856,
      "eloChange": -6,
      "civ": "Sicilians",
      "teamAvgElo": 1014,
      "opponentAvgElo": 1120,
      "teammates": [
        "tmrakshay",
        "紫蝶黄蜂俱有情",
        "ZSeagull"
      ],
      "opponents": [
        "edalmavuz",
        "{R} Parry",
        "Keishi",
        "BaldAfro"
      ]
    },
    {
      "matchId": 484021938,
      "description": "10x 3x BN",
      "mapname": "my map",
      "timestamp": 1780975798,
      "outcome": "win",
      "preRating": 856,
      "postRating": 880,
      "eloChange": 24,
      "civ": "Mongols",
      "teamAvgElo": 1033,
      "opponentAvgElo": 1034,
      "teammates": [
        "procrastination.exe",
        "Wololo",
        "Clean"
      ],
      "opponents": [
        "Keishi",
        "Paris Hilton",
        "bigjames",
        "DR 'TISM"
      ]
    },
    {
      "matchId": 488344482,
      "description": "bamboo nothing 10x",
      "mapname": "my map",
      "timestamp": 1782536020,
      "outcome": "win",
      "preRating": 880,
      "postRating": 904,
      "eloChange": 24,
      "civ": "Vikings",
      "teamAvgElo": 1023,
      "opponentAvgElo": 1076,
      "teammates": [
        "Hughmungus Chungus",
        "Moose",
        "YUJIN"
      ],
      "opponents": [
        "[B] Zennith",
        "pandalam",
        "紫蝶黄蜂俱有情",
        "Xinzzo"
      ]
    },
    {
      "matchId": 489711523,
      "description": "i kun 10x3x 4v4s qun729084973",
      "mapname": "Bamboo Nothing_Paren_V4",
      "timestamp": 1783052901,
      "outcome": "loss",
      "preRating": 904,
      "postRating": 895,
      "eloChange": -9,
      "civ": "Magyars",
      "teamAvgElo": 949,
      "opponentAvgElo": 1059,
      "teammates": [
        "Ellie91",
        "procrastination.exe",
        "DillPickle"
      ],
      "opponents": [
        "i kun 2.5",
        "Xinzzo",
        "fxsound",
        "Wololo"
      ]
    },
    {
      "matchId": 489922925,
      "description": "10x Shared 3xTech Bamboo Nothing",
      "mapname": "Bamboo Nothing_Paren_V4",
      "timestamp": 1783161000,
      "outcome": "loss",
      "preRating": 895,
      "postRating": 886,
      "eloChange": -9,
      "civ": "Vietnamese",
      "teamAvgElo": 1004,
      "opponentAvgElo": 1058,
      "teammates": [
        "procrastination.exe",
        "TheBloodyWall",
        "[B] pro.PHET"
      ],
      "opponents": [
        "{R} Parry",
        "Bao Oninon",
        "Maverick29311",
        "Sal"
      ]
    },
    {
      "matchId": 491685432,
      "description": "10x 3x shared tech Bamboo Nothing Random Civ",
      "mapname": "BAMBOO NOTHING_Paren_v4_nohills",
      "timestamp": 1783810707,
      "outcome": "win",
      "preRating": 886,
      "postRating": 909,
      "eloChange": 23,
      "civ": "Bohemians",
      "teamAvgElo": 973,
      "opponentAvgElo": 1058,
      "teammates": [
        "NoAgendaPODCAST",
        "Yeepers",
        "Monk"
      ],
      "opponents": [
        "PIEROGI",
        "Maxim Liann",
        "疯狂的电脑",
        "Wimac"
      ]
    },
    {
      "matchId": 492030505,
      "description": "bamboo nothing  10x",
      "mapname": "Bamboo Nothing v3 (BaLi)",
      "timestamp": 1783934859,
      "outcome": "win",
      "preRating": 909,
      "postRating": 931,
      "eloChange": 22,
      "civ": "Spanish",
      "teamAvgElo": 1009,
      "opponentAvgElo": 1059,
      "teammates": [
        "平生不修善果 只爱石油军火",
        "ActualWizard",
        "Zavgor"
      ],
      "opponents": [
        "[B] Zennith",
        "cyberocioso",
        "Catwomim",
        "Scipio"
      ]
    },
    {
      "matchId": 492032798,
      "description": "bamboo nothing  10x",
      "mapname": "Bamboo Nothing v3 (BaLi)",
      "timestamp": 1783936091,
      "outcome": "loss",
      "preRating": 931,
      "postRating": 921,
      "eloChange": -10,
      "civ": "Celts",
      "teamAvgElo": 988,
      "opponentAvgElo": 1056,
      "teammates": [
        "ActualWizard",
        "Consume Product",
        "Eemeli"
      ],
      "opponents": [
        "[B] Zennith",
        "鱼浆",
        "平生不修善果 只爱石油军火",
        "Scipio"
      ]
    },
    {
      "matchId": 492632826,
      "description": "10x_3x_Bamboo_Nothing_Random",
      "mapname": "Bamboo Nothing v4 (BaLi)",
      "timestamp": 1784176855,
      "outcome": "loss",
      "preRating": 921,
      "postRating": 911,
      "eloChange": -10,
      "civ": "Bengalis",
      "teamAvgElo": 1014,
      "opponentAvgElo": 1067,
      "teammates": [
        "Contry",
        "pandasadnap",
        "vincentc95"
      ],
      "opponents": [
        "Stigel",
        "Bambamdumm",
        "typ53b90",
        "treehugger"
      ]
    },
    {
      "matchId": 492651411,
      "description": "10x 3x bamboo",
      "mapname": "BAMBOO NOTHING_Paren_v4",
      "timestamp": 1784189362,
      "outcome": "loss",
      "preRating": 911,
      "postRating": 902,
      "eloChange": -9,
      "civ": "Persians",
      "teamAvgElo": 975,
      "opponentAvgElo": 1086,
      "teammates": [
        "DnD",
        "boroinbishop",
        "CristoTheRealCeisto"
      ],
      "opponents": [
        "Lykerya",
        "Lordetion",
        "OldManofStorr",
        "tonkatumura"
      ]
    },
    {
      "matchId": 492792942,
      "description": "10x 3x shared tech Bamboo Nothing Random Civ",
      "mapname": "BAMBOO NOTHING_Paren_v4_nohills",
      "timestamp": 1784242387,
      "outcome": "loss",
      "preRating": 902,
      "postRating": 893,
      "eloChange": -9,
      "civ": "Vietnamese",
      "teamAvgElo": 950,
      "opponentAvgElo": 1077,
      "teammates": [
        "procrastination.exe",
        "Nigerian Farmer",
        "Burt"
      ],
      "opponents": [
        "NoAgendaPODCAST",
        "Nimu.-",
        "Ghost_pt",
        "develement"
      ]
    },
    {
      "matchId": 492828091,
      "description": "10x 3x - bamboo donut",
      "mapname": "BAMBOO NOTHING_waterdonut_test2_v2",
      "timestamp": 1784255844,
      "outcome": "win",
      "preRating": 893,
      "postRating": 914,
      "eloChange": 21,
      "civ": "Malians",
      "teamAvgElo": 1036,
      "opponentAvgElo": 1013,
      "teammates": [
        "Parenquima",
        "Monkeymonk",
        "Peresoso"
      ],
      "opponents": [
        "Optimus",
        "pool_champ",
        "z e o H",
        "BugKaShok"
      ]
    },
    {
      "matchId": 492868162,
      "description": "bamboo nothing 10x",
      "mapname": "Bamboo Nothing v3 (BaLi)",
      "timestamp": 1784276825,
      "outcome": "loss",
      "preRating": 914,
      "postRating": 903,
      "eloChange": -11,
      "civ": "Bulgarians",
      "teamAvgElo": 1001,
      "opponentAvgElo": 1017,
      "teammates": [
        "Evil  Destroyer",
        "476055690",
        "[S33]ff"
      ],
      "opponents": [
        "[B] Zennith",
        "aLEXt",
        "Maxim Liann",
        "AOC_Snake"
      ]
    }
  ]
}