{
  "profile_id": 5464701,
  "alias": "Consume Product",
  "rating": 1088,
  "wins": 133,
  "losses": 184,
  "gamesCount": 317,
  "winRate": 42,
  "lastPlayedAt": 1784506236,
  "country": "fr",
  "merged_ids": [
    5464701,
    12321559
  ],
  "ratingHistory": [
    1000,
    956,
    868,
    923,
    921,
    961,
    989,
    996,
    1012,
    969,
    934,
    903,
    864,
    868,
    873,
    939,
    927,
    957,
    983,
    944,
    908,
    930,
    929,
    988,
    977,
    953,
    946,
    975,
    974,
    983,
    976,
    944,
    1001,
    997,
    1037,
    1020,
    1009,
    999,
    1007,
    1000,
    992,
    957,
    924,
    919,
    919,
    894,
    871,
    926,
    926,
    896,
    870,
    877,
    873,
    877,
    884,
    952,
    940,
    905,
    942,
    942,
    940,
    953,
    978,
    974,
    966,
    1006,
    998,
    987,
    1037,
    1059,
    1060,
    1069,
    1046,
    1060,
    1049,
    1064,
    1078,
    1028,
    1004,
    992,
    1042,
    1023,
    1072,
    1041,
    991,
    1008,
    964,
    946,
    971,
    960,
    985,
    1011,
    988,
    1009,
    1025,
    1070,
    1098,
    1104,
    1108,
    1088
  ],
  "recentMatches": [
    {
      "matchId": 492786374,
      "description": "4vs4 10x 3x shared civ bonus, random civ",
      "mapname": "BAMBOO NOTHING_Paren_v4",
      "timestamp": 1784239612,
      "outcome": "win",
      "preRating": 988,
      "postRating": 1007,
      "eloChange": 19,
      "civ": "Mongols",
      "teamAvgElo": 1037,
      "opponentAvgElo": 1043,
      "teammates": [
        "yimacs_yoyoyo",
        "pool_champ",
        "Apocalypto"
      ],
      "opponents": [
        "Trekkspell",
        "Voskarius",
        "jair_silva",
        "Ricardo V"
      ]
    },
    {
      "matchId": 492791450,
      "description": "4vs4 10x 3x shared civ bonus, random civ",
      "mapname": "BAMBOO NOTHING_Paren_v4",
      "timestamp": 1784241506,
      "outcome": "win",
      "preRating": 1007,
      "postRating": 1024,
      "eloChange": 17,
      "civ": "Japanese",
      "teamAvgElo": 1062,
      "opponentAvgElo": 1030,
      "teammates": [
        "Wololo",
        "kiggless",
        "Delta"
      ],
      "opponents": [
        "yimacs_yoyoyo",
        "gemmascho",
        "Your Ego",
        "Apocalypto"
      ]
    },
    {
      "matchId": 492811949,
      "description": "10x3x Mangrove Nothing",
      "mapname": "Mangrove FN",
      "timestamp": 1784249703,
      "outcome": "loss",
      "preRating": 1024,
      "postRating": 1009,
      "eloChange": -15,
      "civ": "Hindustanis",
      "teamAvgElo": 1024,
      "opponentAvgElo": 1041,
      "teammates": [
        "NoLo",
        "M¤l₫",
        "Lockhart"
      ],
      "opponents": [
        "Imperator Storm",
        "Lordetion",
        "mothysime11",
        "Maxim Liann"
      ]
    },
    {
      "matchId": 492813690,
      "description": "10x_3x_Bamboo_Nothing_Random",
      "mapname": "Bamboo Nothing v4 (BaLi)",
      "timestamp": 1784250534,
      "outcome": "win",
      "preRating": 1009,
      "postRating": 1026,
      "eloChange": 17,
      "civ": "Bohemians",
      "teamAvgElo": 1012,
      "opponentAvgElo": 1030,
      "teammates": [
        "Joeywaterfall",
        "Optimus",
        "LB Trice"
      ],
      "opponents": [
        "Contry",
        "[LWS] Mandatum",
        "Parts",
        "NoLo"
      ]
    },
    {
      "matchId": 492824512,
      "description": "Bamboo 10x Shared 3x Tech",
      "mapname": "BAMBOO NOTHING_Paren_v4_nohills",
      "timestamp": 1784254325,
      "outcome": "loss",
      "preRating": 1026,
      "postRating": 1009,
      "eloChange": -17,
      "civ": "Burmese",
      "teamAvgElo": 1023,
      "opponentAvgElo": 1014,
      "teammates": [
        "Mc Katrina",
        "Optimus",
        "sniper-123"
      ],
      "opponents": [
        "baianitro",
        "LeosMind",
        "pandasadnap",
        "bigjames"
      ]
    },
    {
      "matchId": 492896792,
      "description": "10x Shared Civ Bonus (everything nothing) no goths",
      "mapname": "Bush Nothing",
      "timestamp": 1784292644,
      "outcome": "win",
      "preRating": 1009,
      "postRating": 1025,
      "eloChange": 16,
      "civ": "Cumans",
      "teamAvgElo": 995,
      "opponentAvgElo": 1000,
      "teammates": [
        "Hebo",
        "Antimier",
        "margolumen"
      ],
      "opponents": [
        "WhiteMonk",
        "V3 MUFFIN COMMANDER",
        "ElmoWithoutL",
        "轻绘梨花泪满衣"
      ]
    },
    {
      "matchId": 492902090,
      "description": "10x Shared Civ Bonus (everything nothing)",
      "mapname": "Bush Nothing",
      "timestamp": 1784294849,
      "outcome": "win",
      "preRating": 1025,
      "postRating": 1040,
      "eloChange": 15,
      "civ": "Britons",
      "teamAvgElo": 1024,
      "opponentAvgElo": 1004,
      "teammates": [
        "margolumen",
        "Heisenberg",
        "BeatsNArt"
      ],
      "opponents": [
        "WhiteMonk",
        "Vader",
        "bhasudi--",
        "checkdis"
      ]
    },
    {
      "matchId": 492967895,
      "description": "BAMBOOLA 10x 3x",
      "mapname": "BAMBOO NOTHING - SCORPYON DE",
      "timestamp": 1784314670,
      "outcome": "win",
      "preRating": 1040,
      "postRating": 1056,
      "eloChange": 16,
      "civ": "Spanish",
      "teamAvgElo": 1008,
      "opponentAvgElo": 1030,
      "teammates": [
        "Lozzer",
        "wintre",
        "babeleo"
      ],
      "opponents": [
        "ISwaZz",
        "CountryLunatic",
        "schrubber",
        "RadioActiveMan"
      ]
    },
    {
      "matchId": 492970864,
      "description": "BAMBOOLA 10x 3x",
      "mapname": "BAMBOO NOTHING - SCORPYON DE",
      "timestamp": 1784315388,
      "outcome": "win",
      "preRating": 1056,
      "postRating": 1070,
      "eloChange": 14,
      "civ": "Slavs",
      "teamAvgElo": 1024,
      "opponentAvgElo": 1018,
      "teammates": [
        "CountryLunatic",
        "Bachter",
        "Vader"
      ],
      "opponents": [
        "...",
        "apolizer",
        "RadioActiveMan",
        "ISwaZz"
      ]
    },
    {
      "matchId": 492990206,
      "description": "BAMBOO 10x3xtech",
      "mapname": "BAMBOO NOTHING - SCORPYON DE",
      "timestamp": 1784320502,
      "outcome": "win",
      "preRating": 1070,
      "postRating": 1085,
      "eloChange": 15,
      "civ": "Magyars",
      "teamAvgElo": 1038,
      "opponentAvgElo": 1052,
      "teammates": [
        "yimacs_yoyoyo",
        "Mortak",
        "duckbuildperson"
      ],
      "opponents": [
        "iamatthe.hell",
        "Optimus",
        "Voskarius",
        "Sal"
      ]
    },
    {
      "matchId": 493003019,
      "description": "10x 3x bamboo NO IDIOT",
      "mapname": "BAMBOO NOTHING_Paren_v4",
      "timestamp": 1784324001,
      "outcome": "win",
      "preRating": 1085,
      "postRating": 1102,
      "eloChange": 17,
      "civ": "Vietnamese",
      "teamAvgElo": 1022,
      "opponentAvgElo": 1100,
      "teammates": [
        "TheCobra",
        "Supreme Lord 'Kim Xi Trump'",
        "Chirijiraden"
      ],
      "opponents": [
        "Emusan",
        "Voskarius",
        "herelin0",
        "golhmogh"
      ]
    },
    {
      "matchId": 493032223,
      "description": "10x3x ",
      "mapname": "BAMBOO NOTHING_Paren_v4_nohills",
      "timestamp": 1784333817,
      "outcome": "loss",
      "preRating": 1102,
      "postRating": 1083,
      "eloChange": -19,
      "civ": "Malians",
      "teamAvgElo": 1054,
      "opponentAvgElo": 1030,
      "teammates": [
        "TJ",
        "Tiny Hands",
        "mothysime11"
      ],
      "opponents": [
        "Nigerian Farmer",
        "Given Sens",
        "baianitro",
        "Parenquima"
      ]
    },
    {
      "matchId": 493035889,
      "description": "BAMBOOLA 10x 3x",
      "mapname": "BAMBOO NOTHING - SCORPYON DE",
      "timestamp": 1784334989,
      "outcome": "win",
      "preRating": 1083,
      "postRating": 1098,
      "eloChange": 15,
      "civ": "Tatars",
      "teamAvgElo": 1084,
      "opponentAvgElo": 1057,
      "teammates": [
        "SpiniestTuna222",
        "Nigerian Farmer",
        "田瘾犯了"
      ],
      "opponents": [
        "tacotoy",
        "Wololo",
        "mothysime11",
        "baianitro"
      ]
    },
    {
      "matchId": 493440885,
      "description": "+10x+3xtech   no noob ",
      "mapname": "BAMBOO NOTHING_Paren_v4",
      "timestamp": 1784471300,
      "outcome": "win",
      "preRating": 1098,
      "postRating": 1111,
      "eloChange": 13,
      "civ": "Armenians",
      "teamAvgElo": 1023,
      "opponentAvgElo": 1037,
      "teammates": [
        "拍车面前人人平等",
        "Heklort",
        "0urSneakyBoi"
      ],
      "opponents": [
        "Lumedge",
        "_Zeruch_",
        "Scipio",
        "irvizuett"
      ]
    },
    {
      "matchId": 493447913,
      "description": "+10x+3xtech   no noob ",
      "mapname": "BAMBOO NOTHING_Paren_v4",
      "timestamp": 1784472919,
      "outcome": "win",
      "preRating": 1111,
      "postRating": 1123,
      "eloChange": 12,
      "civ": "Persians",
      "teamAvgElo": 1072,
      "opponentAvgElo": 1017,
      "teammates": [
        "_Zeruch_",
        "R301",
        "Max"
      ],
      "opponents": [
        "拍车面前人人平等",
        "mgmanager",
        "nooblet3300",
        "abatyse6533"
      ]
    },
    {
      "matchId": 493492030,
      "description": "10x 3x BN ",
      "mapname": "BAMBOO NOTHING - SCORPYON DE",
      "timestamp": 1784484523,
      "outcome": "loss",
      "preRating": 1123,
      "postRating": 1104,
      "eloChange": -19,
      "civ": "Bengalis",
      "teamAvgElo": 1022,
      "opponentAvgElo": 1055,
      "teammates": [
        "Lama Kužel",
        "Kalervo Jankko",
        "lul"
      ],
      "opponents": [
        "pool_champ",
        "StreamerOffline",
        "Contry",
        "RA"
      ]
    },
    {
      "matchId": 493507862,
      "description": "10x 3x shared tech Bamboo Nothing Random Civ",
      "mapname": "BAMBOO NOTHING_Paren_v4_nohills",
      "timestamp": 1784489363,
      "outcome": "win",
      "preRating": 1104,
      "postRating": 1116,
      "eloChange": 12,
      "civ": "Franks",
      "teamAvgElo": 1072,
      "opponentAvgElo": 1024,
      "teammates": [
        "NoAgendaPODCAST",
        "Pinguin.exe",
        "Boocer"
      ],
      "opponents": [
        "SpiniestTuna222",
        "thasl",
        "Cubayop",
        "PIEROGI"
      ]
    },
    {
      "matchId": 493518313,
      "description": "BAMBOOLA 10x 3x",
      "mapname": "BAMBOO NOTHING - SCORPYON DE",
      "timestamp": 1784493691,
      "outcome": "win",
      "preRating": 1116,
      "postRating": 1129,
      "eloChange": 13,
      "civ": "Celts",
      "teamAvgElo": 1067,
      "opponentAvgElo": 1059,
      "teammates": [
        "nooblet3300",
        "Scipio",
        "Vince"
      ],
      "opponents": [
        "golhmogh",
        "Mehandor",
        "BeatsNArt",
        "[TodEs] MnTartara"
      ]
    },
    {
      "matchId": 493526820,
      "description": "BAMBOOLA 10x 3x",
      "mapname": "BAMBOO NOTHING - SCORPYON DE",
      "timestamp": 1784498870,
      "outcome": "loss",
      "preRating": 1129,
      "postRating": 1108,
      "eloChange": -21,
      "civ": "Italians",
      "teamAvgElo": 1135,
      "opponentAvgElo": 1014,
      "teammates": [
        "DrompferFTW",
        "田瘾犯了",
        "Nuke Toilet"
      ],
      "opponents": [
        "FPS Geo",
        "PITON | Shepy",
        "iamatthe.hell",
        "Pogonophobia69"
      ]
    },
    {
      "matchId": 493547262,
      "description": "10x Shared 3xTech Bamboo Nothing",
      "mapname": "BAMBOO NOTHING_Paren_v4",
      "timestamp": 1784506236,
      "outcome": "loss",
      "preRating": 1108,
      "postRating": 1088,
      "eloChange": -20,
      "civ": "Bohemians",
      "teamAvgElo": 1084,
      "opponentAvgElo": 1029,
      "teammates": [
        "{R} Parry",
        "DJ",
        "S´korpi0n_43"
      ],
      "opponents": [
        "Mehandor",
        "DPK75",
        "NothingAtAll11",
        "leandrod_c"
      ]
    }
  ]
}